jpeg_decoder_verilog/rtl/entropy/jpeg_huffman_decoder.v
`timescale 1ns/1ps

module jpeg_huffman_decoder (
    input  wire        clk,
    input  wire        rst_n,
    input  wire        enable,      // Chỉ decode/nạp bit khi = 1
    input  wire        start,       // Load table

    // Bitstream Input
    input  wire        bit_in,
    input  wire        bit_valid,

    // Huffman Tables
    input  wire [15:0] huff_code_in [0:255],
    input  wire [4:0]  huff_len_in  [0:255],

    output reg  [7:0]  symbol_out,
    output reg         symbol_valid
);

    // ================= BUFFERS =================
    reg [31:0] shift_buf;
    reg [5:0]  bit_count;

    // ================= TABLES =================
    reg [15:0] tbl_code [0:255];
    reg [4:0]  tbl_len  [0:255];
    integer i;

    // ================= SEARCH SIGNALS =================
    integer k, j;
    reg found;
    reg [4:0] found_len;
    reg [7:0] found_symbol;

    // ================= LOGIC TỔ HỢP TÍNH TOÁN NEXT STATE =================
    // Biến tạm để tính toán giá trị tiếp theo của buffer và count
    reg [31:0] next_shift_buf;
    reg [5:0]  next_bit_count;

    always @(*) begin
        // 1. Mặc định giữ nguyên
        next_shift_buf = shift_buf;
        next_bit_count = bit_count;

        // 2. Nếu có bit mới vào -> Thêm vào buffer
        if (enable && bit_valid) begin
            next_shift_buf = (next_shift_buf << 1) | bit_in;
            next_bit_count = next_bit_count + 1;
        end

        // 3. Nếu tìm thấy Symbol -> Cắt bớt phần đầu buffer
        // Lưu ý: found được tính dựa trên shift_buf CŨ (đã ổn định từ clock trước)
        // Nhưng ta áp dụng cắt bỏ lên next_shift_buf để giữ lại bit mới (nếu có)
        if (enable && found) begin
            if (next_bit_count >= found_len) begin
                // Mask để giữ lại phần dư. VD: Buf=1011 (4 bit), Found=10 (2 bit) -> Dư 11
                // next_bit_count lúc này đã bao gồm cả bit mới (nếu có)
                next_shift_buf = next_shift_buf & ((1 << (next_bit_count - found_len)) - 1);
                next_bit_count = next_bit_count - found_len;
            end else begin
                // Trường hợp hy hữu (lỗi logic nếu xảy ra): reset
                next_shift_buf = 0;
                next_bit_count = 0;
            end
        end
    end

    // ================= MAIN SEQUENTIAL LOGIC =================
    always @(posedge clk or negedge rst_n) begin
        if (!rst_n) begin
            shift_buf    <= 32'd0;
            bit_count    <= 6'd0;
            symbol_out   <= 8'd0;
            symbol_valid <= 1'b0;
            
            // Reset tables (Optional, tốn resource mô phỏng)
            for (i = 0; i < 256; i = i + 1) begin
                tbl_code[i] <= 16'd0;
                tbl_len[i]  <= 5'd0;
            end
        end else begin
            symbol_valid <= 1'b0;

            // Load Tables
            if (start) begin
                for (i = 0; i < 256; i = i + 1) begin
                    tbl_code[i] <= huff_code_in[i];
                    tbl_len[i]  <= huff_len_in[i];
                end
            end

            // Cập nhật Buffer & Count từ logic tổ hợp
            if (enable) begin
                shift_buf <= next_shift_buf;
                bit_count <= next_bit_count;
                
                // Output Symbol nếu tìm thấy
                if (found) begin
                    symbol_out   <= found_symbol;
                    symbol_valid <= 1'b1;
                end
            end
        end
    end

    // ================= LOGIC TÌM KIẾM (COMBINATIONAL) =================
    // Tách phần tìm kiếm ra always @(*) để code gọn hơn
    // Logic này dựa trên shift_buf hiện tại (đã chốt từ clock trước)
    always @(*) begin
        found = 0;
        found_len = 0;
        found_symbol = 0;
        
        if (enable) begin
            for (k = 1; k <= 16; k = k + 1) begin
                // Chỉ tìm nếu chưa thấy và đủ bit
                if (!found && bit_count >= k) begin
                    for (j = 0; j < 256; j = j + 1) begin
                        if (!found && tbl_len[j] == k) begin
                            // So sánh mã: Lấy k bit cao nhất của shift_buf
                            if (tbl_code[j] == (shift_buf >> (bit_count - k))) begin
                                found = 1;
                                found_len = k[4:0];
                                found_symbol = j[7:0];
                            end
                        end
                    end
                end
            end
        end
    end

endmodule

jpeg_decoder_verilog/tb/tb_huffman_decoder.v
`timescale 1ns / 1ps

module tb_huffman_decoder;

    // --- Signals ---
    reg clk;
    reg rst_n;
    reg enable;
    reg start;
    
    // Bitstream Input
    reg bit_in;
    reg bit_valid;

    // Table Interface
    reg [15:0] huff_code_in [0:255];
    reg [4:0]  huff_len_in  [0:255];

    // Output
    wire [7:0] symbol_out;
    wire symbol_valid;

    // --- Instantiate DUT ---
    jpeg_huffman_decoder uut (
        .clk(clk),
        .rst_n(rst_n),
        .enable(enable),
        .start(start),
        
        .bit_in(bit_in),
        .bit_valid(bit_valid),
        
        .huff_code_in(huff_code_in),
        .huff_len_in(huff_len_in),
        
        .symbol_out(symbol_out),
        .symbol_valid(symbol_valid)
    );

    // --- Clock ---
    always #5 clk = ~clk;

    // --- Tasks ---
    task send_bit(input b);
    begin
        @(posedge clk);
        bit_in <= b;
        bit_valid <= 1;
        @(posedge clk);
        bit_valid <= 0;
    end
    endtask

    integer i;

    // --- Test Scenario ---
    initial begin
        $dumpfile("sim/huffman_test.vcd");
        $dumpvars(0, tb_huffman_decoder);

        // Init
        clk = 0; rst_n = 0; enable = 0; start = 0;
        bit_in = 0; bit_valid = 0;
        
        // Clear Table Inputs
        for (i=0; i<256; i=i+1) begin
            huff_code_in[i] = 0;
            huff_len_in[i]  = 0;
        end

        // Setup Huffman Table giả lập (Custom Table)
        // Rule: Canonical Huffman (Mã ngắn bên trái, dài bên phải)
        
        // Symbol 0x0A -> Mã '0' (Len 1)
        huff_code_in[8'h0A] = 16'b0; 
        huff_len_in[8'h0A]  = 5'd1;

        // Symbol 0x0B -> Mã '10' (Len 2)
        huff_code_in[8'h0B] = 16'b10;
        huff_len_in[8'h0B]  = 5'd2;

        // Symbol 0x0C -> Mã '110' (Len 3)
        huff_code_in[8'h0C] = 16'b110;
        huff_len_in[8'h0C]  = 5'd3;

        // Reset Sequence
        #20 rst_n = 1;
        #10;

        // 1. Load Table
        $display("[TEST] Loading Huffman Table...");
        @(posedge clk);
        start <= 1;
        @(posedge clk);
        start <= 0;
        #20; // Chờ load xong (thực ra DUT load trong 1 clock vì dùng array assignment)

        // 2. Start Decoding
        $display("[TEST] Start Decoding...");
        enable <= 1;

        // --- Case 1: Gửi bit '0' -> Expect Symbol 0x0A ---
        send_bit(0); 
        #10; // Chờ decode

        // --- Case 2: Gửi bit '1', sau đó '0' -> Expect Symbol 0x0B ---
        send_bit(1);
        send_bit(0);
        #10;

        // --- Case 3: Gửi '1', '1', '0' -> Expect Symbol 0x0C ---
        send_bit(1);
        send_bit(1);
        send_bit(0);
        #10;

        // --- Case 4: Test Race Condition (Vừa decode xong vừa nạp bit mới) ---
        // Giả sử DUT vừa decode xong 0x0C, buffer đang trống.
        // Ta gửi liên tiếp 2 mã '0' (0x0A) sát nhau
        $display("[TEST] Fast stream...");
        send_bit(0); // Decode ra 0x0A ngay lập tức
        send_bit(0); // Decode ra 0x0A tiếp theo
        
        #50;
        $finish;
    end

    // --- Monitor Output ---
    always @(posedge clk) begin
        if (symbol_valid) begin
            $display("[OUT] Time %t | Found Symbol: %h", $time, symbol_out);
        end
    end

endmodule

jpeg_decoder_verilog/sim/huffman_test.vcd
$date
	Sat Jan 03 14:40:44 2026
$end
$version
	Icarus Verilog
$end
$timescale
	1ps
$end
$scope module tb_huffman_decoder $end
$var wire 1 ! symbol_valid $end
$var wire 8 " symbol_out [7:0] $end
$var reg 1 # bit_in $end
$var reg 1 $ bit_valid $end
$var reg 1 % clk $end
$var reg 1 & enable $end
$var reg 1 ' rst_n $end
$var reg 1 ( start $end
$var integer 32 ) i [31:0] $end
$scope module uut $end
$var wire 1 # bit_in $end
$var wire 1 $ bit_valid $end
$var wire 1 % clk $end
$var wire 1 & enable $end
$var wire 1 ' rst_n $end
$var wire 1 ( start $end
$var reg 6 * bit_count [5:0] $end
$var reg 1 + found $end
$var reg 5 , found_len [4:0] $end
$var reg 8 - found_symbol [7:0] $end
$var reg 6 . next_bit_count [5:0] $end
$var reg 32 / next_shift_buf [31:0] $end
$var reg 32 0 shift_buf [31:0] $end
$var reg 8 1 symbol_out [7:0] $end
$var reg 1 ! symbol_valid $end
$var integer 32 2 i [31:0] $end
$var integer 32 3 j [31:0] $end
$var integer 32 4 k [31:0] $end
$upscope $end
$scope task send_bit $end
$var reg 1 5 b $end
$upscope $end
$upscope $end
$enddefinitions $end
$comment Show the parameter values. $end
$dumpall
$end
#0
$dumpvars
x5
bx 4
bx 3
b100000000 2
b0 1
b0 0
b0 /
b0 .
b0 -
b0 ,
0+
b0 *
b100000000 )
0(
0'
0&
0%
0$
0#
b0 "
0!
$end
#5000
b100000000 2
1%
#10000
0%
#15000
b100000000 2
1%
#20000
0%
1'
#25000
1%
#30000
0%
#35000
1(
1%
#40000
0%
#45000
0(
b100000000 2
1%
#50000
0%
#55000
1%
#60000
0%
#65000
b10001 4
b1 .
1$
1&
1%
05
#70000
0%
#75000
b0 .
b1010 -
b1 ,
1+
b100000000 3
b10001 4
b1 *
0$
1%
#80000
0%
#85000
b10001 4
b0 -
b0 ,
0+
b1 .
b1 /
1!
b1010 "
b1010 1
b0 *
1$
1#
1%
15
#90000
0%
#95000
b100000000 3
b10001 4
b1 *
b1 0
0!
0$
05
1%
#100000
0%
#105000
b10 .
b10 /
1$
0#
1%
#110000
0%
#115000
b0 .
b0 /
b1011 -
b10 ,
1+
b100000000 3
b10001 4
b10 *
b10 0
0$
1%
#120000
0%
#125000
b10001 4
b0 -
b0 ,
0+
b1 .
b1 /
1!
b1011 "
b1011 1
b0 *
b0 0
1$
1#
1%
15
#130000
0%
#135000
b100000000 3
b10001 4
b1 *
b1 0
0!
0$
1%
#140000
0%
#145000
b10 .
b11 /
1$
1%
#150000
0%
#155000
b100000000 3
b10001 4
b10 *
b11 0
0$
05
1%
#160000
0%
#165000
b11 .
b110 /
1$
0#
1%
#170000
0%
#175000
b0 .
b0 /
b1100 -
b11 ,
1+
b100000000 3
b10001 4
b11 *
b110 0
0$
1%
#180000
0%
#185000
b10001 4
b0 -
b0 ,
0+
b1 .
1!
b1100 "
b1100 1
b0 *
b0 0
1$
1%
#190000
0%
#195000
b0 .
b1010 -
b1 ,
1+
b100000000 3
b10001 4
b1 *
0!
0$
1%
#200000
0%
#205000
b10001 4
b0 -
b0 ,
0+
b1 .
1!
b1010 "
b1010 1
b0 *
1$
1%
#210000
0%
#215000
b0 .
b1010 -
b1 ,
1+
b100000000 3
b10001 4
b1 *
0!
0$
1%
#220000
0%
#225000
b10001 4
b0 -
b0 ,
0+
1!
b0 *
1%
#230000
0%
#235000
0!
1%
